f8s/__init__.py
f8s/command.py
f8s/extension.py
f8s/py.typed
f8s/tools.py
f8s-0.2.2.dist-info/entry_points.txt
f8s-0.2.2.dist-info/WHEEL
f8s-0.2.2.dist-info/METADATA
f8s-0.2.2.dist-info/licenses/LICENSE
f8s-0.2.2.dist-info/RECORD
