Metadata-Version: 2.1
Name: f8s
Version: 0.2.2
Summary: Framework for building K8s-ready Flask applications.
License: MIT
Keywords: Flask,Kubernetes,K8s,F8s,Helm,ArgoCD
Author-email: Alex Braun <alexander.g.braun@gmail.com>
Requires-Python: >=3.10
Classifier: Development Status :: 4 - Beta
Classifier: Intended Audience :: Developers
Classifier: License :: OSI Approved :: MIT License
Classifier: Programming Language :: Python :: 3
Classifier: Programming Language :: Python :: 3.10
Classifier: Typing :: Typed
Requires-Dist: click>=8.1.3
Requires-Dist: flasgger
Requires-Dist: flask
Requires-Dist: flask-healthz
Requires-Dist: gunicorn>=21.2.0
Requires-Dist: pyyaml>=6.0.1
Project-URL: documentation, https://theNewFlesh.github.io/f8s
Project-URL: repository, https://github.com/the-new-flesh/f8s
